ris/__init__.py
ris/cli.py
ris/ris.py
risify-1.2.5.dist-info/licenses/LICENSE
risify-1.2.5.dist-info/METADATA
risify-1.2.5.dist-info/WHEEL
risify-1.2.5.dist-info/entry_points.txt
risify-1.2.5.dist-info/top_level.txt
risify-1.2.5.dist-info/RECORD
