Metadata-Version: 2.4
Name: RISify
Version: 1.2.5
Summary: Simplifies the encoding and decoding of Regional Indicator Symbols
Author-email: "M.P. van de Weerd" <michael@parcifal.dev>
License-Expression: AGPL-3.0-only
Project-URL: Homepage, https://gitlab.com/parcifal/ris-py
Project-URL: Bug Tracker, https://gitlab.com/parcifal/ris-py/-/issues
Keywords: unicode,regional indicator symbols,encoding,decoding,flags,internationalization,localization,emoji
Classifier: Development Status :: 5 - Production/Stable
Classifier: Intended Audience :: Developers
License-File: LICENSE
Requires-Dist: tomli
Requires-Dist: markupsafe
Provides-Extra: dev
Requires-Dist: pylint; extra == "dev"
Requires-Dist: pytest; extra == "dev"
Requires-Dist: pytest-cov; extra == "dev"
Requires-Dist: coverage; extra == "dev"
Dynamic: license-file
